[
  {
    "word": "promoter",
    "description": "A substance added in small amounts to a catalyst to increase its activity",
    "x": 2,
    "y": 0,
    "vertical": true
  },
  {
    "word": "bud",
    "description": "A small pointed lump that appears on a tree or plant and develops into a leaf or flower",
    "x": 8,
    "y": 0,
    "vertical": true
  },
  {
    "word": "spur",
    "description": "To make a change or event happen faster or sooner",
    "x": 4,
    "y": 1,
    "vertical": true
  },
  {
    "word": "compound",
    "description": "A substance that contains atoms of two or more chemical elements held together by chemical bonds",
    "x": 0,
    "y": 3,
    "vertical": false
  },
  {
    "word": "tank",
    "description": "A large container or reservoir for the storage of liquids or gases",
    "x": 9,
    "y": 4,
    "vertical": true
  },
  {
    "word": "coordinate",
    "description": "To work together, esp harmoniously",
    "x": 0,
    "y": 5,
    "vertical": false
  },
  {
    "word": "stiff",
    "description": "Not easily bent; rigid; inflexible",
    "x": 12,
    "y": 6,
    "vertical": true
  },
  {
    "word": "prod",
    "description": "To poke or jab with or as if with a pointed object",
    "x": 14,
    "y": 6,
    "vertical": true
  },
  {
    "word": "coax",
    "description": "To work on or tend (something) carefully and patiently so as to make it function as one desires",
    "x": 8,
    "y": 7,
    "vertical": true
  },
  {
    "word": "kick-start",
    "description": "To make (something) active, functional, or productive again",
    "x": 5,
    "y": 8,
    "vertical": false
  }
]